aliases/__init__.py
aliases/dict.py
aliases/pandas_accessor.py
aliases/polars_accessor.py
aliases/processor.py
aliases/space.py
aliases/string.py
aliases/string_function.py
aliases/third_party_classes.py
aliases-0.6.2.dist-info/METADATA
aliases-0.6.2.dist-info/WHEEL
aliases-0.6.2.dist-info/licenses/LICENSE
aliases-0.6.2.dist-info/RECORD
